<?xml version="1.0" encoding="UTF-8" standalone="yes"?>
<DefaultGearData xmlns:xsi="http://www.w3.org/2001/XMLSchema-instance">
	<Gear>
		<id>1</id>
		<scriptId>170100</scriptId>
		<resourceURI>Suit01</resourceURI>
		<thumbnailURI>Suit01</thumbnailURI>
		<gearType>1</gearType>
		<minAP>0</minAP>
		<maxAP>0</maxAP>
		<ammo>0</ammo>
		<minIAD>0</minIAD>
		<maxIAD>0</maxIAD>
		<addIA>0</addIA>
		<spendIA>0</spendIA>
		<addHP>0</addHP>
		<spendMP>0</spendMP>
		<addMP>0</addMP>
		<makeTime>0</makeTime>
		<makeCost>0</makeCost>
		<makeResource>0</makeResource>
		<makeResourceType>0</makeResourceType>
		<upNextId>0</upNextId>
	</Gear>
	<Gear>
		<id>2</id>
		<scriptId>170101</scriptId>
		<resourceURI>Airframe01</resourceURI>
		<thumbnailURI>Body01</thumbnailURI>
		<gearType>3</gearType>
		<minAP>0</minAP>
		<maxAP>0</maxAP>
		<ammo>0</ammo>
		<minIAD>0</minIAD>
		<maxIAD>0</maxIAD>
		<addIA>0</addIA>
		<spendIA>0</spendIA>
		<addHP>0</addHP>
		<spendMP>5</spendMP>
		<addMP>0</addMP>
		<makeTime>0</makeTime>
		<makeCost>0</makeCost>
		<makeResource>0</makeResource>
		<makeResourceType>0</makeResourceType>
		<upNextId>0</upNextId>
	</Gear>
	<Gear>
		<id>3</id>
		<scriptId>170102</scriptId>
		<resourceURI>Engine01</resourceURI>
		<thumbnailURI>Engine01</thumbnailURI>
		<gearType>2</gearType>
		<minAP>0</minAP>
		<maxAP>0</maxAP>
		<ammo>0</ammo>
		<minIAD>0</minIAD>
		<maxIAD>0</maxIAD>
		<addIA>0</addIA>
		<spendIA>0</spendIA>
		<addHP>0</addHP>
		<spendMP>5</spendMP>
		<addMP>0</addMP>
		<makeTime>0</makeTime>
		<makeCost>0</makeCost>
		<makeResource>0</makeResource>
		<makeResourceType>0</makeResourceType>
		<upNextId>0</upNextId>
	</Gear>
	<Gear>
		<id>4</id>
		<scriptId>170103</scriptId>
		<resourceURI>Weapon01</resourceURI>
		<thumbnailURI>Gun01</thumbnailURI>
		<gearType>4</gearType>
		<minAP>5</minAP>
		<maxAP>10</maxAP>
		<ammo>-1</ammo>
		<minIAD>0</minIAD>
		<maxIAD>0</maxIAD>
		<addIA>1</addIA>
		<spendIA>0</spendIA>
		<addHP>0</addHP>
		<spendMP>5</spendMP>
		<addMP>0</addMP>
		<makeTime>0</makeTime>
		<makeCost>0</makeCost>
		<makeResource>0</makeResource>
		<makeResourceType>0</makeResourceType>
		<upNextId>0</upNextId>
	</Gear>
	<Gear>
		<id>5</id>
		<scriptId>170104</scriptId>
		<resourceURI>Suit02</resourceURI>
		<thumbnailURI>Suit02</thumbnailURI>
		<gearType>1</gearType>
		<minAP>0</minAP>
		<maxAP>0</maxAP>
		<ammo>0</ammo>
		<minIAD>0</minIAD>
		<maxIAD>0</maxIAD>
		<addIA>0</addIA>
		<spendIA>2</spendIA>
		<addHP>0</addHP>
		<spendMP>0</spendMP>
		<addMP>2</addMP>
		<makeTime>5</makeTime>
		<makeCost>300</makeCost>
		<makeResource>0</makeResource>
		<makeResourceType>0</makeResourceType>
		<upNextId>14</upNextId>
	</Gear>
	<Gear>
		<id>6</id>
		<scriptId>170105</scriptId>
		<resourceURI>Airframe02</resourceURI>
		<thumbnailURI>Body02</thumbnailURI>
		<gearType>3</gearType>
		<minAP>0</minAP>
		<maxAP>0</maxAP>
		<ammo>0</ammo>
		<minIAD>0</minIAD>
		<maxIAD>0</maxIAD>
		<addIA>2</addIA>
		<spendIA>0</spendIA>
		<addHP>5</addHP>
		<spendMP>7</spendMP>
		<addMP>0</addMP>
		<makeTime>50</makeTime>
		<makeCost>500</makeCost>
		<makeResource>0</makeResource>
		<makeResourceType>0</makeResourceType>
		<upNextId>15</upNextId>
	</Gear>
	<Gear>
		<id>7</id>
		<scriptId>170106</scriptId>
		<resourceURI>Engine02</resourceURI>
		<thumbnailURI>Engine02</thumbnailURI>
		<gearType>2</gearType>
		<minAP>0</minAP>
		<maxAP>0</maxAP>
		<ammo>0</ammo>
		<minIAD>0</minIAD>
		<maxIAD>0</maxIAD>
		<addIA>0</addIA>
		<spendIA>2</spendIA>
		<addHP>0</addHP>
		<spendMP>7</spendMP>
		<addMP>0</addMP>
		<makeTime>30</makeTime>
		<makeCost>400</makeCost>
		<makeResource>0</makeResource>
		<makeResourceType>0</makeResourceType>
		<upNextId>16</upNextId>
	</Gear>
	<Gear>
		<id>8</id>
		<scriptId>170107</scriptId>
		<resourceURI>Weapon02</resourceURI>
		<thumbnailURI>Gun02</thumbnailURI>
		<gearType>4</gearType>
		<minAP>7</minAP>
		<maxAP>12</maxAP>
		<ammo>-1</ammo>
		<minIAD>0</minIAD>
		<maxIAD>0</maxIAD>
		<addIA>3</addIA>
		<spendIA>0</spendIA>
		<addHP>0</addHP>
		<spendMP>7</spendMP>
		<addMP>0</addMP>
		<makeTime>60</makeTime>
		<makeCost>600</makeCost>
		<makeResource>0</makeResource>
		<makeResourceType>0</makeResourceType>
		<upNextId>17</upNextId>
	</Gear>
	<Gear>
		<id>9</id>
		<scriptId>170109</scriptId>
		<resourceURI>Suit03</resourceURI>
		<thumbnailURI>Suit03</thumbnailURI>
		<gearType>1</gearType>
		<minAP>0</minAP>
		<maxAP>0</maxAP>
		<ammo>0</ammo>
		<minIAD>0</minIAD>
		<maxIAD>0</maxIAD>
		<addIA>0</addIA>
		<spendIA>4</spendIA>
		<addHP>0</addHP>
		<spendMP>0</spendMP>
		<addMP>4</addMP>
		<makeTime>120</makeTime>
		<makeCost>900</makeCost>
		<makeResource>1</makeResource>
		<makeResourceType>1</makeResourceType>
		<upNextId>18</upNextId>
	</Gear>
	<Gear>
		<id>10</id>
		<scriptId>170110</scriptId>
		<resourceURI>Airframe03</resourceURI>
		<thumbnailURI>Body03</thumbnailURI>
		<gearType>3</gearType>
		<minAP>0</minAP>
		<maxAP>0</maxAP>
		<ammo>0</ammo>
		<minIAD>0</minIAD>
		<maxIAD>0</maxIAD>
		<addIA>4</addIA>
		<spendIA>0</spendIA>
		<addHP>8</addHP>
		<spendMP>9</spendMP>
		<addMP>0</addMP>
		<makeTime>300</makeTime>
		<makeCost>1200</makeCost>
		<makeResource>1</makeResource>
		<makeResourceType>1</makeResourceType>
		<upNextId>19</upNextId>
	</Gear>
	<Gear>
		<id>11</id>
		<scriptId>170111</scriptId>
		<resourceURI>Engine03</resourceURI>
		<thumbnailURI>Engine03</thumbnailURI>
		<gearType>2</gearType>
		<minAP>0</minAP>
		<maxAP>0</maxAP>
		<ammo>0</ammo>
		<minIAD>0</minIAD>
		<maxIAD>0</maxIAD>
		<addIA>0</addIA>
		<spendIA>4</spendIA>
		<addHP>0</addHP>
		<spendMP>9</spendMP>
		<addMP>0</addMP>
		<makeTime>600</makeTime>
		<makeCost>1100</makeCost>
		<makeResource>1</makeResource>
		<makeResourceType>1</makeResourceType>
		<upNextId>20</upNextId>
	</Gear>
	<Gear>
		<id>12</id>
		<scriptId>170112</scriptId>
		<resourceURI>Weapon03</resourceURI>
		<thumbnailURI>Gun03</thumbnailURI>
		<gearType>4</gearType>
		<minAP>11</minAP>
		<maxAP>16</maxAP>
		<ammo>-1</ammo>
		<minIAD>0</minIAD>
		<maxIAD>0</maxIAD>
		<addIA>5</addIA>
		<spendIA>0</spendIA>
		<addHP>0</addHP>
		<spendMP>9</spendMP>
		<addMP>0</addMP>
		<makeTime>900</makeTime>
		<makeCost>1400</makeCost>
		<makeResource>1</makeResource>
		<makeResourceType>1</makeResourceType>
		<upNextId>21</upNextId>
	</Gear>
	<Gear>
		<id>13</id>
		<scriptId>170113</scriptId>
		<resourceURI>Weapon04</resourceURI>
		<thumbnailURI>Rocket01</thumbnailURI>
		<gearType>5</gearType>
		<minAP>6</minAP>
		<maxAP>25</maxAP>
		<ammo>2</ammo>
		<minIAD>0</minIAD>
		<maxIAD>10</maxIAD>
		<addIA>6</addIA>
		<spendIA>0</spendIA>
		<addHP>0</addHP>
		<spendMP>11</spendMP>
		<addMP>0</addMP>
		<makeTime>900</makeTime>
		<makeCost>1500</makeCost>
		<makeResource>1</makeResource>
		<makeResourceType>1</makeResourceType>
		<upNextId>22</upNextId>
	</Gear>
	<Gear>
		<id>14</id>
		<scriptId>170114</scriptId>
		<resourceURI>Suit02-1</resourceURI>
		<thumbnailURI>Suit02-1</thumbnailURI>
		<gearType>1</gearType>
		<minAP>0</minAP>
		<maxAP>0</maxAP>
		<ammo>0</ammo>
		<minIAD>0</minIAD>
		<maxIAD>0</maxIAD>
		<addIA>0</addIA>
		<spendIA>3</spendIA>
		<addHP>0</addHP>
		<spendMP>0</spendMP>
		<addMP>3</addMP>
		<makeTime>0</makeTime>
		<makeCost>300</makeCost>
		<makeResource>0</makeResource>
		<makeResourceType>0</makeResourceType>
		<upNextId>23</upNextId>
	</Gear>
	<Gear>
		<id>15</id>
		<scriptId>170115</scriptId>
		<resourceURI>Airframe02-1</resourceURI>
		<thumbnailURI>Body02-1</thumbnailURI>
		<gearType>3</gearType>
		<minAP>0</minAP>
		<maxAP>0</maxAP>
		<ammo>0</ammo>
		<minIAD>0</minIAD>
		<maxIAD>0</maxIAD>
		<addIA>3</addIA>
		<spendIA>0</spendIA>
		<addHP>6</addHP>
		<spendMP>8</spendMP>
		<addMP>0</addMP>
		<makeTime>0</makeTime>
		<makeCost>500</makeCost>
		<makeResource>0</makeResource>
		<makeResourceType>0</makeResourceType>
		<upNextId>24</upNextId>
	</Gear>
	<Gear>
		<id>16</id>
		<scriptId>170116</scriptId>
		<resourceURI>Engine02-1</resourceURI>
		<thumbnailURI>Engine02-1</thumbnailURI>
		<gearType>2</gearType>
		<minAP>0</minAP>
		<maxAP>0</maxAP>
		<ammo>0</ammo>
		<minIAD>0</minIAD>
		<maxIAD>0</maxIAD>
		<addIA>0</addIA>
		<spendIA>3</spendIA>
		<addHP>0</addHP>
		<spendMP>8</spendMP>
		<addMP>0</addMP>
		<makeTime>0</makeTime>
		<makeCost>400</makeCost>
		<makeResource>0</makeResource>
		<makeResourceType>0</makeResourceType>
		<upNextId>25</upNextId>
	</Gear>
	<Gear>
		<id>17</id>
		<scriptId>170117</scriptId>
		<resourceURI>Weapon02-1</resourceURI>
		<thumbnailURI>Gun02-1</thumbnailURI>
		<gearType>4</gearType>
		<minAP>9</minAP>
		<maxAP>13</maxAP>
		<ammo>-1</ammo>
		<minIAD>0</minIAD>
		<maxIAD>0</maxIAD>
		<addIA>4</addIA>
		<spendIA>0</spendIA>
		<addHP>0</addHP>
		<spendMP>8</spendMP>
		<addMP>0</addMP>
		<makeTime>0</makeTime>
		<makeCost>600</makeCost>
		<makeResource>0</makeResource>
		<makeResourceType>0</makeResourceType>
		<upNextId>26</upNextId>
	</Gear>
	<Gear>
		<id>18</id>
		<scriptId>170118</scriptId>
		<resourceURI>Suit03-1</resourceURI>
		<thumbnailURI>Suit03-1</thumbnailURI>
		<gearType>1</gearType>
		<minAP>0</minAP>
		<maxAP>0</maxAP>
		<ammo>0</ammo>
		<minIAD>0</minIAD>
		<maxIAD>0</maxIAD>
		<addIA>0</addIA>
		<spendIA>6</spendIA>
		<addHP>0</addHP>
		<spendMP>0</spendMP>
		<addMP>6</addMP>
		<makeTime>0</makeTime>
		<makeCost>900</makeCost>
		<makeResource>1</makeResource>
		<makeResourceType>1</makeResourceType>
		<upNextId>0</upNextId>
	</Gear>
	<Gear>
		<id>19</id>
		<scriptId>170119</scriptId>
		<resourceURI>Airframe03-1</resourceURI>
		<thumbnailURI>Body03-1</thumbnailURI>
		<gearType>3</gearType>
		<minAP>0</minAP>
		<maxAP>0</maxAP>
		<ammo>0</ammo>
		<minIAD>0</minIAD>
		<maxIAD>0</maxIAD>
		<addIA>6</addIA>
		<spendIA>0</spendIA>
		<addHP>10</addHP>
		<spendMP>11</spendMP>
		<addMP>0</addMP>
		<makeTime>0</makeTime>
		<makeCost>1200</makeCost>
		<makeResource>1</makeResource>
		<makeResourceType>1</makeResourceType>
		<upNextId>0</upNextId>
	</Gear>
	<Gear>
		<id>20</id>
		<scriptId>170120</scriptId>
		<resourceURI>Engine03-1</resourceURI>
		<thumbnailURI>Engine03-1</thumbnailURI>
		<gearType>2</gearType>
		<minAP>0</minAP>
		<maxAP>0</maxAP>
		<ammo>0</ammo>
		<minIAD>0</minIAD>
		<maxIAD>0</maxIAD>
		<addIA>0</addIA>
		<spendIA>6</spendIA>
		<addHP>0</addHP>
		<spendMP>11</spendMP>
		<addMP>0</addMP>
		<makeTime>0</makeTime>
		<makeCost>1100</makeCost>
		<makeResource>1</makeResource>
		<makeResourceType>1</makeResourceType>
		<upNextId>0</upNextId>
	</Gear>
	<Gear>
		<id>21</id>
		<scriptId>170121</scriptId>
		<resourceURI>Weapon03-1</resourceURI>
		<thumbnailURI>Gun03-1</thumbnailURI>
		<gearType>4</gearType>
		<minAP>14</minAP>
		<maxAP>19</maxAP>
		<ammo>-1</ammo>
		<minIAD>0</minIAD>
		<maxIAD>0</maxIAD>
		<addIA>5</addIA>
		<spendIA>0</spendIA>
		<addHP>0</addHP>
		<spendMP>13</spendMP>
		<addMP>0</addMP>
		<makeTime>0</makeTime>
		<makeCost>1400</makeCost>
		<makeResource>1</makeResource>
		<makeResourceType>1</makeResourceType>
		<upNextId>0</upNextId>
	</Gear>
	<Gear>
		<id>22</id>
		<scriptId>170122</scriptId>
		<resourceURI>Weapon04-1</resourceURI>
		<thumbnailURI>Rocket01-1</thumbnailURI>
		<gearType>5</gearType>
		<minAP>9</minAP>
		<maxAP>25</maxAP>
		<ammo>2</ammo>
		<minIAD>2</minIAD>
		<maxIAD>10</maxIAD>
		<addIA>6</addIA>
		<spendIA>0</spendIA>
		<addHP>0</addHP>
		<spendMP>11</spendMP>
		<addMP>0</addMP>
		<makeTime>0</makeTime>
		<makeCost>1500</makeCost>
		<makeResource>1</makeResource>
		<makeResourceType>1</makeResourceType>
		<upNextId>0</upNextId>
	</Gear>
	<Gear>
		<id>23</id>
		<scriptId>170123</scriptId>
		<resourceURI>Suit02-2</resourceURI>
		<thumbnailURI>Suit02-2</thumbnailURI>
		<gearType>1</gearType>
		<minAP>0</minAP>
		<maxAP>0</maxAP>
		<ammo>0</ammo>
		<minIAD>0</minIAD>
		<maxIAD>0</maxIAD>
		<addIA>0</addIA>
		<spendIA>4</spendIA>
		<addHP>0</addHP>
		<spendMP>0</spendMP>
		<addMP>5</addMP>
		<makeTime>0</makeTime>
		<makeCost>300</makeCost>
		<makeResource>0</makeResource>
		<makeResourceType>0</makeResourceType>
		<upNextId>0</upNextId>
	</Gear>
	<Gear>
		<id>24</id>
		<scriptId>170124</scriptId>
		<resourceURI>Airframe02-2</resourceURI>
		<thumbnailURI>Body02-2</thumbnailURI>
		<gearType>3</gearType>
		<minAP>0</minAP>
		<maxAP>0</maxAP>
		<ammo>0</ammo>
		<minIAD>0</minIAD>
		<maxIAD>0</maxIAD>
		<addIA>4</addIA>
		<spendIA>0</spendIA>
		<addHP>8</addHP>
		<spendMP>9</spendMP>
		<addMP>0</addMP>
		<makeTime>0</makeTime>
		<makeCost>500</makeCost>
		<makeResource>0</makeResource>
		<makeResourceType>0</makeResourceType>
		<upNextId>0</upNextId>
	</Gear>
	<Gear>
		<id>25</id>
		<scriptId>170125</scriptId>
		<resourceURI>Engine02-2</resourceURI>
		<thumbnailURI>Engine02-2</thumbnailURI>
		<gearType>2</gearType>
		<minAP>0</minAP>
		<maxAP>0</maxAP>
		<ammo>0</ammo>
		<minIAD>0</minIAD>
		<maxIAD>0</maxIAD>
		<addIA>0</addIA>
		<spendIA>4</spendIA>
		<addHP>0</addHP>
		<spendMP>9</spendMP>
		<addMP>0</addMP>
		<makeTime>0</makeTime>
		<makeCost>400</makeCost>
		<makeResource>0</makeResource>
		<makeResourceType>0</makeResourceType>
		<upNextId>0</upNextId>
	</Gear>
	<Gear>
		<id>26</id>
		<scriptId>170126</scriptId>
		<resourceURI>Weapon02-2</resourceURI>
		<thumbnailURI>Gun02-2</thumbnailURI>
		<gearType>4</gearType>
		<minAP>12</minAP>
		<maxAP>16</maxAP>
		<ammo>-1</ammo>
		<minIAD>0</minIAD>
		<maxIAD>0</maxIAD>
		<addIA>5</addIA>
		<spendIA>0</spendIA>
		<addHP>0</addHP>
		<spendMP>11</spendMP>
		<addMP>0</addMP>
		<makeTime>0</makeTime>
		<makeCost>600</makeCost>
		<makeResource>0</makeResource>
		<makeResourceType>0</makeResourceType>
		<upNextId>0</upNextId>
	</Gear>
	<Gear>
		<id>27</id>
		<scriptId>170127</scriptId>
		<resourceURI>Suit04</resourceURI>
		<thumbnailURI>Suit04</thumbnailURI>
		<gearType>1</gearType>
		<minAP>0</minAP>
		<maxAP>0</maxAP>
		<ammo>0</ammo>
		<minIAD>0</minIAD>
		<maxIAD>0</maxIAD>
		<addIA>0</addIA>
		<spendIA>6</spendIA>
		<addHP>0</addHP>
		<spendMP>0</spendMP>
		<addMP>8</addMP>
		<makeTime>1800</makeTime>
		<makeCost>1800</makeCost>
		<makeResource>2</makeResource>
		<makeResourceType>1</makeResourceType>
		<upNextId>32</upNextId>
	</Gear>
	<Gear>
		<id>28</id>
		<scriptId>170128</scriptId>
		<resourceURI>Airframe04</resourceURI>
		<thumbnailURI>Body04</thumbnailURI>
		<gearType>3</gearType>
		<minAP>0</minAP>
		<maxAP>0</maxAP>
		<ammo>0</ammo>
		<minIAD>0</minIAD>
		<maxIAD>0</maxIAD>
		<addIA>6</addIA>
		<spendIA>0</spendIA>
		<addHP>11</addHP>
		<spendMP>11</spendMP>
		<addMP>0</addMP>
		<makeTime>2200</makeTime>
		<makeCost>2200</makeCost>
		<makeResource>2</makeResource>
		<makeResourceType>1</makeResourceType>
		<upNextId>33</upNextId>
	</Gear>
	<Gear>
		<id>29</id>
		<scriptId>170129</scriptId>
		<resourceURI>Engine04</resourceURI>
		<thumbnailURI>Engine04</thumbnailURI>
		<gearType>2</gearType>
		<minAP>0</minAP>
		<maxAP>0</maxAP>
		<ammo>0</ammo>
		<minIAD>0</minIAD>
		<maxIAD>0</maxIAD>
		<addIA>0</addIA>
		<spendIA>6</spendIA>
		<addHP>0</addHP>
		<spendMP>11</spendMP>
		<addMP>0</addMP>
		<makeTime>2600</makeTime>
		<makeCost>2600</makeCost>
		<makeResource>2</makeResource>
		<makeResourceType>1</makeResourceType>
		<upNextId>34</upNextId>
	</Gear>
	<Gear>
		<id>30</id>
		<scriptId>170130</scriptId>
		<resourceURI>Weapon05</resourceURI>
		<thumbnailURI>Gun04</thumbnailURI>
		<gearType>4</gearType>
		<minAP>17</minAP>
		<maxAP>22</maxAP>
		<ammo>-1</ammo>
		<minIAD>0</minIAD>
		<maxIAD>0</maxIAD>
		<addIA>7</addIA>
		<spendIA>0</spendIA>
		<addHP>0</addHP>
		<spendMP>11</spendMP>
		<addMP>0</addMP>
		<makeTime>3000</makeTime>
		<makeCost>3000</makeCost>
		<makeResource>2</makeResource>
		<makeResourceType>1</makeResourceType>
		<upNextId>35</upNextId>
	</Gear>
	<Gear>
		<id>31</id>
		<scriptId>170131</scriptId>
		<resourceURI>Weapon06</resourceURI>
		<thumbnailURI>Rocket02</thumbnailURI>
		<gearType>5</gearType>
		<minAP>10</minAP>
		<maxAP>29</maxAP>
		<ammo>3</ammo>
		<minIAD>4</minIAD>
		<maxIAD>14</maxIAD>
		<addIA>8</addIA>
		<spendIA>0</spendIA>
		<addHP>0</addHP>
		<spendMP>13</spendMP>
		<addMP>0</addMP>
		<makeTime>3400</makeTime>
		<makeCost>3200</makeCost>
		<makeResource>2</makeResource>
		<makeResourceType>1</makeResourceType>
		<upNextId>36</upNextId>
	</Gear>
	<Gear>
		<id>32</id>
		<scriptId>170132</scriptId>
		<resourceURI>Suit04-1</resourceURI>
		<thumbnailURI>Suit04-1</thumbnailURI>
		<gearType>1</gearType>
		<minAP>0</minAP>
		<maxAP>0</maxAP>
		<ammo>0</ammo>
		<minIAD>0</minIAD>
		<maxIAD>0</maxIAD>
		<addIA>0</addIA>
		<spendIA>7</spendIA>
		<addHP>0</addHP>
		<spendMP>0</spendMP>
		<addMP>12</addMP>
		<makeTime>0</makeTime>
		<makeCost>1800</makeCost>
		<makeResource>2</makeResource>
		<makeResourceType>1</makeResourceType>
		<upNextId>0</upNextId>
	</Gear>
	<Gear>
		<id>33</id>
		<scriptId>170133</scriptId>
		<resourceURI>Airframe04-1</resourceURI>
		<thumbnailURI>Body04-1</thumbnailURI>
		<gearType>3</gearType>
		<minAP>0</minAP>
		<maxAP>0</maxAP>
		<ammo>0</ammo>
		<minIAD>0</minIAD>
		<maxIAD>0</maxIAD>
		<addIA>7</addIA>
		<spendIA>0</spendIA>
		<addHP>12</addHP>
		<spendMP>12</spendMP>
		<addMP>0</addMP>
		<makeTime>0</makeTime>
		<makeCost>2200</makeCost>
		<makeResource>2</makeResource>
		<makeResourceType>1</makeResourceType>
		<upNextId>0</upNextId>
	</Gear>
	<Gear>
		<id>34</id>
		<scriptId>170134</scriptId>
		<resourceURI>Engine04-1</resourceURI>
		<thumbnailURI>Engine04-1</thumbnailURI>
		<gearType>2</gearType>
		<minAP>0</minAP>
		<maxAP>0</maxAP>
		<ammo>0</ammo>
		<minIAD>0</minIAD>
		<maxIAD>0</maxIAD>
		<addIA>0</addIA>
		<spendIA>7</spendIA>
		<addHP>0</addHP>
		<spendMP>12</spendMP>
		<addMP>0</addMP>
		<makeTime>0</makeTime>
		<makeCost>2600</makeCost>
		<makeResource>2</makeResource>
		<makeResourceType>1</makeResourceType>
		<upNextId>0</upNextId>
	</Gear>
	<Gear>
		<id>35</id>
		<scriptId>170135</scriptId>
		<resourceURI>Weapon05-1</resourceURI>
		<thumbnailURI>Gun04-1</thumbnailURI>
		<gearType>4</gearType>
		<minAP>21</minAP>
		<maxAP>26</maxAP>
		<ammo>-1</ammo>
		<minIAD>0</minIAD>
		<maxIAD>0</maxIAD>
		<addIA>8</addIA>
		<spendIA>0</spendIA>
		<addHP>0</addHP>
		<spendMP>12</spendMP>
		<addMP>0</addMP>
		<makeTime>0</makeTime>
		<makeCost>3000</makeCost>
		<makeResource>2</makeResource>
		<makeResourceType>1</makeResourceType>
		<upNextId>0</upNextId>
	</Gear>
	<Gear>
		<id>36</id>
		<scriptId>170136</scriptId>
		<resourceURI>Weapon06-1</resourceURI>
		<thumbnailURI>Rocket02-1</thumbnailURI>
		<gearType>5</gearType>
		<minAP>13</minAP>
		<maxAP>32</maxAP>
		<ammo>3</ammo>
		<minIAD>7</minIAD>
		<maxIAD>17</maxIAD>
		<addIA>9</addIA>
		<spendIA>0</spendIA>
		<addHP>0</addHP>
		<spendMP>14</spendMP>
		<addMP>0</addMP>
		<makeTime>0</makeTime>
		<makeCost>3200</makeCost>
		<makeResource>2</makeResource>
		<makeResourceType>1</makeResourceType>
		<upNextId>0</upNextId>
	</Gear>
	<Gear>
		<id>120</id>
		<scriptId>170100</scriptId>
		<resourceURI>0</resourceURI>
		<thumbnailURI>0</thumbnailURI>
		<gearType>7</gearType>
		<minAP>8</minAP>
		<maxAP>12</maxAP>
		<ammo>-1</ammo>
		<minIAD>0</minIAD>
		<maxIAD>0</maxIAD>
		<addIA>0</addIA>
		<spendIA>0</spendIA>
		<addHP>0</addHP>
		<spendMP>0</spendMP>
		<addMP>0</addMP>
		<makeTime>0</makeTime>
		<makeCost>0</makeCost>
		<makeResource>0</makeResource>
		<makeResourceType>0</makeResourceType>
		<upNextId>0</upNextId>
	</Gear>
	<Gear>
		<id>121</id>
		<scriptId>170100</scriptId>
		<resourceURI>0</resourceURI>
		<thumbnailURI>0</thumbnailURI>
		<gearType>7</gearType>
		<minAP>14</minAP>
		<maxAP>16</maxAP>
		<ammo>-1</ammo>
		<minIAD>0</minIAD>
		<maxIAD>5</maxIAD>
		<addIA>0</addIA>
		<spendIA>0</spendIA>
		<addHP>0</addHP>
		<spendMP>0</spendMP>
		<addMP>0</addMP>
		<makeTime>0</makeTime>
		<makeCost>0</makeCost>
		<makeResource>0</makeResource>
		<makeResourceType>0</makeResourceType>
		<upNextId>0</upNextId>
	</Gear>
	<Gear>
		<id>122</id>
		<scriptId>170100</scriptId>
		<resourceURI>0</resourceURI>
		<thumbnailURI>0</thumbnailURI>
		<gearType>7</gearType>
		<minAP>20</minAP>
		<maxAP>24</maxAP>
		<ammo>-1</ammo>
		<minIAD>0</minIAD>
		<maxIAD>10</maxIAD>
		<addIA>0</addIA>
		<spendIA>0</spendIA>
		<addHP>0</addHP>
		<spendMP>0</spendMP>
		<addMP>0</addMP>
		<makeTime>0</makeTime>
		<makeCost>0</makeCost>
		<makeResource>0</makeResource>
		<makeResourceType>0</makeResourceType>
		<upNextId>0</upNextId>
	</Gear>
</DefaultGearData>